freeplay_langgraph/__init__.py
freeplay_langgraph/client.py
freeplay_langgraph/freeplay_agent.py
freeplay_langgraph/middleware.py
freeplay_langgraph/normalized_message.py
freeplay_langgraph/otel_attributes.py
freeplay_langgraph/py.typed
freeplay_langgraph-0.4.0.dist-info/METADATA
freeplay_langgraph-0.4.0.dist-info/WHEEL
freeplay_langgraph-0.4.0.dist-info/RECORD
