Metadata-Version: 2.4
Name: freeplay-langgraph
Version: 0.4.0
Summary: Freeplay integration for LangGraph and LangChain
Author-email: Engineering at Freeplay <engineering@freeplay.ai>
Requires-Python: >=3.10
Requires-Dist: freeplay>=0.1.0
Requires-Dist: langchain-community>=0.3.0
Requires-Dist: langchain-core>=0.3.0
Requires-Dist: langchain>=1.0.0
Requires-Dist: langgraph>=0.2.0
Requires-Dist: openinference-instrumentation-langchain>=0.1.0
Requires-Dist: opentelemetry-exporter-otlp-proto-http>=1.35.0
Requires-Dist: opentelemetry-sdk>=1.35.0
